{
  "text": "Were there any of these entities then incarnated in second density before the 75,000 years? I am Ra. This is incorrect. These particular entities were incarnate in time space, third density, that is the so-called inner planes undergoing the process of healing and approaching realization of their action.",
  "timestamps": {
    "segment": [
      {
        "segment": "Were there any of these entities then incarnated in second density before the 75,000 years?",
        "start_offset": 18,
        "end_offset": 90,
        "start": 1.44,
        "end": 7.2
      },
      {
        "segment": "I am Ra.",
        "start_offset": 133,
        "end_offset": 161,
        "start": 10.64,
        "end": 12.88
      },
      {
        "segment": "This is incorrect.",
        "start_offset": 188,
        "end_offset": 236,
        "start": 15.040000000000001,
        "end": 18.88
      },
      {
        "segment": "These particular entities were incarnate in time space, third density, that is the so-called inner planes undergoing the process of healing and approaching realization of their action.",
        "start_offset": 262,
        "end_offset": 752,
        "start": 20.96,
        "end": 60.160000000000004
      }
    ],
    "word": [
      {
        "word": "Were",
        "start_offset": 18,
        "end_offset": 24,
        "start": 1.44,
        "end": 1.92
      },
      {
        "word": "there",
        "start_offset": 24,
        "end_offset": 27,
        "start": 1.92,
        "end": 2.16
      },
      {
        "word": "any",
        "start_offset": 27,
        "end_offset": 30,
        "start": 2.16,
        "end": 2.4
      },
      {
        "word": "of",
        "start_offset": 30,
        "end_offset": 32,
        "start": 2.4,
        "end": 2.56
      },
      {
        "word": "these",
        "start_offset": 32,
        "end_offset": 35,
        "start": 2.56,
        "end": 2.8000000000000003
      },
      {
        "word": "entities",
        "start_offset": 35,
        "end_offset": 42,
        "start": 2.8000000000000003,
        "end": 3.36
      },
      {
        "word": "then",
        "start_offset": 42,
        "end_offset": 46,
        "start": 3.36,
        "end": 3.68
      },
      {
        "word": "incarnated",
        "start_offset": 46,
        "end_offset": 55,
        "start": 3.68,
        "end": 4.4
      },
      {
        "word": "in",
        "start_offset": 55,
        "end_offset": 57,
        "start": 4.4,
        "end": 4.5600000000000005
      },
      {
        "word": "second",
        "start_offset": 57,
        "end_offset": 62,
        "start": 4.5600000000000005,
        "end": 4.96
      },
      {
        "word": "density",
        "start_offset": 62,
        "end_offset": 69,
        "start": 4.96,
        "end": 5.5200000000000005
      },
      {
        "word": "before",
        "start_offset": 69,
        "end_offset": 72,
        "start": 5.5200000000000005,
        "end": 5.76
      },
      {
        "word": "the",
        "start_offset": 72,
        "end_offset": 74,
        "start": 5.76,
        "end": 5.92
      },
      {
        "word": "75,000",
        "start_offset": 74,
        "end_offset": 87,
        "start": 5.92,
        "end": 6.96
      },
      {
        "word": "years?",
        "start_offset": 88,
        "end_offset": 90,
        "start": 7.04,
        "end": 7.2
      },
      {
        "word": "I",
        "start_offset": 133,
        "end_offset": 137,
        "start": 10.64,
        "end": 10.96
      },
      {
        "word": "am",
        "start_offset": 145,
        "end_offset": 149,
        "start": 11.6,
        "end": 11.92
      },
      {
        "word": "Ra.",
        "start_offset": 157,
        "end_offset": 161,
        "start": 12.56,
        "end": 12.88
      },
      {
        "word": "This",
        "start_offset": 188,
        "end_offset": 192,
        "start": 15.040000000000001,
        "end": 15.36
      },
      {
        "word": "is",
        "start_offset": 200,
        "end_offset": 204,
        "start": 16.0,
        "end": 16.32
      },
      {
        "word": "incorrect.",
        "start_offset": 220,
        "end_offset": 236,
        "start": 17.6,
        "end": 18.88
      },
      {
        "word": "These",
        "start_offset": 262,
        "end_offset": 266,
        "start": 20.96,
        "end": 21.28
      },
      {
        "word": "particular",
        "start_offset": 274,
        "end_offset": 290,
        "start": 21.92,
        "end": 23.2
      },
      {
        "word": "entities",
        "start_offset": 298,
        "end_offset": 314,
        "start": 23.84,
        "end": 25.12
      },
      {
        "word": "were",
        "start_offset": 330,
        "end_offset": 334,
        "start": 26.400000000000002,
        "end": 26.72
      },
      {
        "word": "incarnate",
        "start_offset": 346,
        "end_offset": 361,
        "start": 27.68,
        "end": 28.88
      },
      {
        "word": "in",
        "start_offset": 372,
        "end_offset": 376,
        "start": 29.76,
        "end": 30.080000000000002
      },
      {
        "word": "time",
        "start_offset": 380,
        "end_offset": 384,
        "start": 30.400000000000002,
        "end": 30.72
      },
      {
        "word": "space,",
        "start_offset": 387,
        "end_offset": 394,
        "start": 30.96,
        "end": 31.52
      },
      {
        "word": "third",
        "start_offset": 406,
        "end_offset": 414,
        "start": 32.480000000000004,
        "end": 33.12
      },
      {
        "word": "density,",
        "start_offset": 414,
        "end_offset": 426,
        "start": 33.12,
        "end": 34.08
      },
      {
        "word": "that",
        "start_offset": 439,
        "end_offset": 443,
        "start": 35.12,
        "end": 35.44
      },
      {
        "word": "is",
        "start_offset": 443,
        "end_offset": 447,
        "start": 35.44,
        "end": 35.76
      },
      {
        "word": "the",
        "start_offset": 460,
        "end_offset": 464,
        "start": 36.800000000000004,
        "end": 37.12
      },
      {
        "word": "so-called",
        "start_offset": 472,
        "end_offset": 490,
        "start": 37.76,
        "end": 39.2
      },
      {
        "word": "inner",
        "start_offset": 498,
        "end_offset": 506,
        "start": 39.84,
        "end": 40.480000000000004
      },
      {
        "word": "planes",
        "start_offset": 510,
        "end_offset": 518,
        "start": 40.800000000000004,
        "end": 41.44
      },
      {
        "word": "undergoing",
        "start_offset": 538,
        "end_offset": 554,
        "start": 43.04,
        "end": 44.32
      },
      {
        "word": "the",
        "start_offset": 570,
        "end_offset": 574,
        "start": 45.6,
        "end": 45.92
      },
      {
        "word": "process",
        "start_offset": 578,
        "end_offset": 586,
        "start": 46.24,
        "end": 46.88
      },
      {
        "word": "of",
        "start_offset": 602,
        "end_offset": 606,
        "start": 48.160000000000004,
        "end": 48.480000000000004
      },
      {
        "word": "healing",
        "start_offset": 610,
        "end_offset": 622,
        "start": 48.800000000000004,
        "end": 49.76
      },
      {
        "word": "and",
        "start_offset": 634,
        "end_offset": 638,
        "start": 50.72,
        "end": 51.04
      },
      {
        "word": "approaching",
        "start_offset": 662,
        "end_offset": 678,
        "start": 52.96,
        "end": 54.24
      },
      {
        "word": "realization",
        "start_offset": 688,
        "end_offset": 704,
        "start": 55.04,
        "end": 56.32
      },
      {
        "word": "of",
        "start_offset": 720,
        "end_offset": 724,
        "start": 57.6,
        "end": 57.92
      },
      {
        "word": "their",
        "start_offset": 732,
        "end_offset": 736,
        "start": 58.56,
        "end": 58.88
      },
      {
        "word": "action.",
        "start_offset": 744,
        "end_offset": 752,
        "start": 59.52,
        "end": 60.160000000000004
      }
    ]
  },
  "metadata": {
    "source_file": "021-07.mp3",
    "audio_duration": 61.05,
    "transcription_time": 0.12,
    "rtfx": 495.36,
    "timestamp": "2026-01-06T21:48:25.650004+00:00"
  }
}