{
  "text": "This is very revealing to us. Thank you. Each of us gets the signals and dreams. I have been aware of clairaudient communication at least once in waking up. Can you suggest a method whereby we might, shall I say, nullify the effect of the influence that we don't want from a negative source? I am Ra. There are various methods. We shall offer the most available or simple. To share the difficult contact with the other-selves associated with this working and to meditate in love for these senders of images and light for self and other-selves is the most available means of nullifying the effects of such occurrences. To downgrade these experiences by the use of intellect or the disciplines of will is to invite the prolonging of the effects. Far better then to share in trust such experiences and join hearts and souls in love and light with compassion for the sender and armor for the self.",
  "timestamps": {
    "segment": [
      {
        "segment": "This is very revealing to us.",
        "start_offset": 0,
        "end_offset": 29,
        "start": 2.2,
        "end": 3.88
      },
      {
        "segment": "Thank you.",
        "start_offset": 30,
        "end_offset": 40,
        "start": 4.48,
        "end": 4.88
      },
      {
        "segment": "Each of us gets the signals and dreams.",
        "start_offset": 41,
        "end_offset": 80,
        "start": 8.581,
        "end": 15.822
      },
      {
        "segment": "I have been aware of clairaudient communication at least once in waking up.",
        "start_offset": 81,
        "end_offset": 156,
        "start": 17.362,
        "end": 23.342
      },
      {
        "segment": "Can you suggest a method whereby we might, shall I say, nullify the effect of the influence that we don't want from a negative source?",
        "start_offset": 157,
        "end_offset": 291,
        "start": 30.643,
        "end": 57.285
      },
      {
        "segment": "I am Ra.",
        "start_offset": 292,
        "end_offset": 300,
        "start": 57.485,
        "end": 59.586
      },
      {
        "segment": "There are various methods.",
        "start_offset": 301,
        "end_offset": 327,
        "start": 61.666,
        "end": 66.966
      },
      {
        "segment": "We shall offer the most available or simple.",
        "start_offset": 328,
        "end_offset": 372,
        "start": 68.247,
        "end": 81.168
      },
      {
        "segment": "To share the difficult contact with the other-selves associated with this working and to meditate in love for these senders of images and light for self and other-selves is the most available means of nullifying the effects of such occurrences.",
        "start_offset": 373,
        "end_offset": 617,
        "start": 84.128,
        "end": 157.755
      },
      {
        "segment": "To downgrade these experiences by the use of intellect or the disciplines of will is to invite the prolonging of the effects.",
        "start_offset": 618,
        "end_offset": 743,
        "start": 160.315,
        "end": 193.678
      },
      {
        "segment": "Far better then to share in trust such experiences and join hearts and souls in love and light with compassion for the sender and armor for the self.",
        "start_offset": 744,
        "end_offset": 893,
        "start": 195.299,
        "end": 234.662
      }
    ],
    "word": [
      {
        "word": "This",
        "start_offset": 0,
        "end_offset": 4,
        "start": 2.2,
        "end": 2.36,
        "score": -7.9655
      },
      {
        "word": "is",
        "start_offset": 5,
        "end_offset": 7,
        "start": 2.42,
        "end": 2.46,
        "score": -8.4871
      },
      {
        "word": "very",
        "start_offset": 8,
        "end_offset": 12,
        "start": 2.98,
        "end": 3.1,
        "score": -8.5705
      },
      {
        "word": "revealing",
        "start_offset": 13,
        "end_offset": 22,
        "start": 3.12,
        "end": 3.52,
        "score": -5.7262
      },
      {
        "word": "to",
        "start_offset": 23,
        "end_offset": 25,
        "start": 3.56,
        "end": 3.62,
        "score": -4.6479
      },
      {
        "word": "us.",
        "start_offset": 26,
        "end_offset": 29,
        "start": 3.74,
        "end": 3.88,
        "score": -5.3302
      },
      {
        "word": "Thank",
        "start_offset": 30,
        "end_offset": 35,
        "start": 4.48,
        "end": 4.7,
        "score": -5.9278
      },
      {
        "word": "you.",
        "start_offset": 36,
        "end_offset": 40,
        "start": 4.74,
        "end": 4.88,
        "score": -8.8892
      },
      {
        "word": "Each",
        "start_offset": 41,
        "end_offset": 45,
        "start": 8.581,
        "end": 8.761,
        "score": -3.145
      },
      {
        "word": "of",
        "start_offset": 46,
        "end_offset": 48,
        "start": 8.801,
        "end": 8.901,
        "score": -3.1667
      },
      {
        "word": "us",
        "start_offset": 49,
        "end_offset": 51,
        "start": 9.001,
        "end": 9.221,
        "score": -3.1204
      },
      {
        "word": "gets",
        "start_offset": 52,
        "end_offset": 56,
        "start": 10.541,
        "end": 10.921,
        "score": -3.1972
      },
      {
        "word": "the",
        "start_offset": 57,
        "end_offset": 60,
        "start": 11.521,
        "end": 11.601,
        "score": -3.9792
      },
      {
        "word": "signals",
        "start_offset": 61,
        "end_offset": 68,
        "start": 11.721,
        "end": 12.241,
        "score": -3.9162
      },
      {
        "word": "and",
        "start_offset": 69,
        "end_offset": 72,
        "start": 13.981,
        "end": 14.221,
        "score": -3.3064
      },
      {
        "word": "dreams.",
        "start_offset": 73,
        "end_offset": 80,
        "start": 15.221,
        "end": 15.822,
        "score": -2.4178
      },
      {
        "word": "I",
        "start_offset": 81,
        "end_offset": 82,
        "start": 17.362,
        "end": 17.382,
        "score": -3.8896
      },
      {
        "word": "have",
        "start_offset": 83,
        "end_offset": 87,
        "start": 17.402,
        "end": 17.562,
        "score": -6.5216
      },
      {
        "word": "been",
        "start_offset": 88,
        "end_offset": 92,
        "start": 17.582,
        "end": 17.802,
        "score": -4.3838
      },
      {
        "word": "aware",
        "start_offset": 93,
        "end_offset": 98,
        "start": 18.322,
        "end": 18.682,
        "score": -3.7774
      },
      {
        "word": "of",
        "start_offset": 99,
        "end_offset": 101,
        "start": 18.762,
        "end": 18.882,
        "score": -3.931
      },
      {
        "word": "clairaudient",
        "start_offset": 102,
        "end_offset": 114,
        "start": 19.742,
        "end": 20.442,
        "score": -6.0305
      },
      {
        "word": "communication",
        "start_offset": 115,
        "end_offset": 128,
        "start": 20.482,
        "end": 21.222,
        "score": -5.2095
      },
      {
        "word": "at",
        "start_offset": 129,
        "end_offset": 131,
        "start": 21.402,
        "end": 21.502,
        "score": -8.7024
      },
      {
        "word": "least",
        "start_offset": 132,
        "end_offset": 137,
        "start": 21.522,
        "end": 21.762,
        "score": -7.2686
      },
      {
        "word": "once",
        "start_offset": 138,
        "end_offset": 142,
        "start": 21.902,
        "end": 22.142,
        "score": -7.0767
      },
      {
        "word": "in",
        "start_offset": 143,
        "end_offset": 145,
        "start": 22.782,
        "end": 22.822,
        "score": -7.1099
      },
      {
        "word": "waking",
        "start_offset": 146,
        "end_offset": 152,
        "start": 22.842,
        "end": 23.162,
        "score": -3.7131
      },
      {
        "word": "up.",
        "start_offset": 153,
        "end_offset": 156,
        "start": 23.222,
        "end": 23.342,
        "score": -3.5157
      },
      {
        "word": "Can",
        "start_offset": 157,
        "end_offset": 160,
        "start": 30.643,
        "end": 30.903,
        "score": -2.2331
      },
      {
        "word": "you",
        "start_offset": 161,
        "end_offset": 164,
        "start": 30.983,
        "end": 31.103,
        "score": -4.4941
      },
      {
        "word": "suggest",
        "start_offset": 165,
        "end_offset": 172,
        "start": 33.903,
        "end": 34.483,
        "score": -2.7843
      },
      {
        "word": "a",
        "start_offset": 173,
        "end_offset": 174,
        "start": 34.583,
        "end": 34.603,
        "score": -4.1856
      },
      {
        "word": "method",
        "start_offset": 175,
        "end_offset": 181,
        "start": 34.723,
        "end": 35.103,
        "score": -2.7936
      },
      {
        "word": "whereby",
        "start_offset": 182,
        "end_offset": 189,
        "start": 35.703,
        "end": 36.203,
        "score": -5.5795
      },
      {
        "word": "we",
        "start_offset": 190,
        "end_offset": 192,
        "start": 36.724,
        "end": 36.824,
        "score": -3.4595
      },
      {
        "word": "might,",
        "start_offset": 193,
        "end_offset": 199,
        "start": 36.924,
        "end": 37.244,
        "score": -3.2124
      },
      {
        "word": "shall",
        "start_offset": 200,
        "end_offset": 205,
        "start": 42.964,
        "end": 43.284,
        "score": -6.8276
      },
      {
        "word": "I",
        "start_offset": 206,
        "end_offset": 207,
        "start": 43.344,
        "end": 43.364,
        "score": -6.2836
      },
      {
        "word": "say,",
        "start_offset": 208,
        "end_offset": 212,
        "start": 43.424,
        "end": 43.624,
        "score": -4.5917
      },
      {
        "word": "nullify",
        "start_offset": 213,
        "end_offset": 220,
        "start": 44.184,
        "end": 44.704,
        "score": -5.7617
      },
      {
        "word": "the",
        "start_offset": 221,
        "end_offset": 224,
        "start": 44.804,
        "end": 44.884,
        "score": -2.8444
      },
      {
        "word": "effect",
        "start_offset": 225,
        "end_offset": 231,
        "start": 44.924,
        "end": 45.364,
        "score": -2.9773
      },
      {
        "word": "of",
        "start_offset": 232,
        "end_offset": 234,
        "start": 45.484,
        "end": 45.564,
        "score": -3.6334
      },
      {
        "word": "the",
        "start_offset": 235,
        "end_offset": 238,
        "start": 45.604,
        "end": 45.684,
        "score": -2.9363
      },
      {
        "word": "influence",
        "start_offset": 239,
        "end_offset": 248,
        "start": 45.764,
        "end": 46.204,
        "score": -3.0075
      },
      {
        "word": "that",
        "start_offset": 249,
        "end_offset": 253,
        "start": 46.224,
        "end": 46.324,
        "score": -7.785
      },
      {
        "word": "we",
        "start_offset": 254,
        "end_offset": 256,
        "start": 46.344,
        "end": 46.424,
        "score": -3.4916
      },
      {
        "word": "don't",
        "start_offset": 257,
        "end_offset": 262,
        "start": 46.504,
        "end": 46.764,
        "score": -4.9632
      },
      {
        "word": "want",
        "start_offset": 263,
        "end_offset": 267,
        "start": 47.425,
        "end": 47.785,
        "score": -4.1766
      },
      {
        "word": "from",
        "start_offset": 268,
        "end_offset": 272,
        "start": 48.205,
        "end": 48.445,
        "score": -3.042
      },
      {
        "word": "a",
        "start_offset": 273,
        "end_offset": 274,
        "start": 49.445,
        "end": 49.465,
        "score": -7.4313
      },
      {
        "word": "negative",
        "start_offset": 275,
        "end_offset": 283,
        "start": 49.485,
        "end": 49.905,
        "score": -3.7006
      },
      {
        "word": "source?",
        "start_offset": 284,
        "end_offset": 291,
        "start": 49.945,
        "end": 57.285,
        "score": -5.0659
      },
      {
        "word": "I",
        "start_offset": 292,
        "end_offset": 293,
        "start": 57.485,
        "end": 57.505,
        "score": -1.1671
      },
      {
        "word": "am",
        "start_offset": 294,
        "end_offset": 296,
        "start": 58.366,
        "end": 58.646,
        "score": -4.2845
      },
      {
        "word": "Ra.",
        "start_offset": 297,
        "end_offset": 300,
        "start": 59.466,
        "end": 59.586,
        "score": -1.2394
      },
      {
        "word": "There",
        "start_offset": 301,
        "end_offset": 306,
        "start": 61.666,
        "end": 62.086,
        "score": -0.9201
      },
      {
        "word": "are",
        "start_offset": 307,
        "end_offset": 310,
        "start": 63.346,
        "end": 63.646,
        "score": -1.2562
      },
      {
        "word": "various",
        "start_offset": 311,
        "end_offset": 318,
        "start": 64.466,
        "end": 65.286,
        "score": -0.7733
      },
      {
        "word": "methods.",
        "start_offset": 319,
        "end_offset": 327,
        "start": 66.246,
        "end": 66.966,
        "score": -0.7462
      },
      {
        "word": "We",
        "start_offset": 328,
        "end_offset": 330,
        "start": 68.247,
        "end": 68.387,
        "score": -0.7378
      },
      {
        "word": "shall",
        "start_offset": 331,
        "end_offset": 336,
        "start": 69.187,
        "end": 69.667,
        "score": -0.8769
      },
      {
        "word": "offer",
        "start_offset": 337,
        "end_offset": 342,
        "start": 70.607,
        "end": 71.087,
        "score": -0.7653
      },
      {
        "word": "the",
        "start_offset": 343,
        "end_offset": 346,
        "start": 72.327,
        "end": 72.487,
        "score": -2.0877
      },
      {
        "word": "most",
        "start_offset": 347,
        "end_offset": 351,
        "start": 74.127,
        "end": 74.647,
        "score": -2.1522
      },
      {
        "word": "available",
        "start_offset": 352,
        "end_offset": 361,
        "start": 77.227,
        "end": 78.547,
        "score": -0.9164
      },
      {
        "word": "or",
        "start_offset": 362,
        "end_offset": 364,
        "start": 79.368,
        "end": 79.648,
        "score": -0.7281
      },
      {
        "word": "simple.",
        "start_offset": 365,
        "end_offset": 372,
        "start": 80.528,
        "end": 81.168,
        "score": -0.8277
      },
      {
        "word": "To",
        "start_offset": 373,
        "end_offset": 375,
        "start": 84.128,
        "end": 84.508,
        "score": -1.1216
      },
      {
        "word": "share",
        "start_offset": 376,
        "end_offset": 381,
        "start": 85.268,
        "end": 85.868,
        "score": -1.0125
      },
      {
        "word": "the",
        "start_offset": 382,
        "end_offset": 385,
        "start": 87.668,
        "end": 87.848,
        "score": -0.8233
      },
      {
        "word": "difficult",
        "start_offset": 386,
        "end_offset": 395,
        "start": 89.068,
        "end": 90.449,
        "score": -1.2054
      },
      {
        "word": "contact",
        "start_offset": 396,
        "end_offset": 403,
        "start": 91.629,
        "end": 92.809,
        "score": -0.7097
      },
      {
        "word": "with",
        "start_offset": 404,
        "end_offset": 408,
        "start": 94.049,
        "end": 94.549,
        "score": -1.3463
      },
      {
        "word": "the",
        "start_offset": 409,
        "end_offset": 412,
        "start": 95.749,
        "end": 95.929,
        "score": -0.9168
      },
      {
        "word": "other-selves",
        "start_offset": 413,
        "end_offset": 425,
        "start": 96.929,
        "end": 98.629,
        "score": -1.8008
      },
      {
        "word": "associated",
        "start_offset": 426,
        "end_offset": 436,
        "start": 99.87,
        "end": 102.05,
        "score": -0.7472
      },
      {
        "word": "with",
        "start_offset": 437,
        "end_offset": 441,
        "start": 103.17,
        "end": 103.63,
        "score": -1.0366
      },
      {
        "word": "this",
        "start_offset": 442,
        "end_offset": 446,
        "start": 104.29,
        "end": 104.73,
        "score": -0.8273
      },
      {
        "word": "working",
        "start_offset": 447,
        "end_offset": 454,
        "start": 105.61,
        "end": 106.35,
        "score": -0.7086
      },
      {
        "word": "and",
        "start_offset": 455,
        "end_offset": 458,
        "start": 107.77,
        "end": 108.17,
        "score": -0.7727
      },
      {
        "word": "to",
        "start_offset": 459,
        "end_offset": 461,
        "start": 108.57,
        "end": 108.87,
        "score": -1.1562
      },
      {
        "word": "meditate",
        "start_offset": 462,
        "end_offset": 470,
        "start": 110.15,
        "end": 111.671,
        "score": -0.824
      },
      {
        "word": "in",
        "start_offset": 471,
        "end_offset": 473,
        "start": 113.191,
        "end": 113.511,
        "score": -0.7659
      },
      {
        "word": "love",
        "start_offset": 474,
        "end_offset": 478,
        "start": 114.331,
        "end": 114.911,
        "score": -0.7801
      },
      {
        "word": "for",
        "start_offset": 479,
        "end_offset": 482,
        "start": 116.011,
        "end": 116.451,
        "score": -0.7941
      },
      {
        "word": "these",
        "start_offset": 483,
        "end_offset": 488,
        "start": 118.151,
        "end": 118.831,
        "score": -1.161
      },
      {
        "word": "senders",
        "start_offset": 489,
        "end_offset": 496,
        "start": 119.911,
        "end": 120.812,
        "score": -0.8204
      },
      {
        "word": "of",
        "start_offset": 497,
        "end_offset": 499,
        "start": 121.772,
        "end": 122.072,
        "score": -0.8755
      },
      {
        "word": "images",
        "start_offset": 500,
        "end_offset": 506,
        "start": 122.972,
        "end": 124.052,
        "score": -0.7569
      },
      {
        "word": "and",
        "start_offset": 507,
        "end_offset": 510,
        "start": 125.572,
        "end": 125.932,
        "score": -0.8275
      },
      {
        "word": "light",
        "start_offset": 511,
        "end_offset": 516,
        "start": 126.412,
        "end": 126.992,
        "score": -0.8053
      },
      {
        "word": "for",
        "start_offset": 517,
        "end_offset": 520,
        "start": 128.632,
        "end": 129.112,
        "score": -0.7422
      },
      {
        "word": "self",
        "start_offset": 521,
        "end_offset": 525,
        "start": 129.892,
        "end": 130.432,
        "score": -0.7094
      },
      {
        "word": "and",
        "start_offset": 526,
        "end_offset": 529,
        "start": 131.533,
        "end": 131.893,
        "score": -3.7698
      },
      {
        "word": "other-selves",
        "start_offset": 530,
        "end_offset": 542,
        "start": 132.553,
        "end": 134.013,
        "score": -0.8442
      },
      {
        "word": "is",
        "start_offset": 543,
        "end_offset": 545,
        "start": 135.953,
        "end": 136.373,
        "score": -5.7452
      },
      {
        "word": "the",
        "start_offset": 546,
        "end_offset": 549,
        "start": 137.033,
        "end": 137.193,
        "score": -1.9805
      },
      {
        "word": "most",
        "start_offset": 550,
        "end_offset": 554,
        "start": 138.633,
        "end": 139.173,
        "score": -0.7246
      },
      {
        "word": "available",
        "start_offset": 555,
        "end_offset": 564,
        "start": 139.933,
        "end": 141.373,
        "score": -0.8754
      },
      {
        "word": "means",
        "start_offset": 565,
        "end_offset": 570,
        "start": 142.594,
        "end": 143.354,
        "score": -0.7222
      },
      {
        "word": "of",
        "start_offset": 571,
        "end_offset": 573,
        "start": 144.734,
        "end": 145.114,
        "score": -1.1551
      },
      {
        "word": "nullifying",
        "start_offset": 574,
        "end_offset": 584,
        "start": 147.034,
        "end": 148.554,
        "score": -1.9113
      },
      {
        "word": "the",
        "start_offset": 585,
        "end_offset": 588,
        "start": 149.714,
        "end": 149.874,
        "score": -1.1929
      },
      {
        "word": "effects",
        "start_offset": 589,
        "end_offset": 596,
        "start": 150.994,
        "end": 152.195,
        "score": -0.9267
      },
      {
        "word": "of",
        "start_offset": 597,
        "end_offset": 599,
        "start": 153.515,
        "end": 153.855,
        "score": -3.1524
      },
      {
        "word": "such",
        "start_offset": 600,
        "end_offset": 604,
        "start": 154.595,
        "end": 155.015,
        "score": -3.3013
      },
      {
        "word": "occurrences.",
        "start_offset": 605,
        "end_offset": 617,
        "start": 155.955,
        "end": 157.755,
        "score": -1.4671
      },
      {
        "word": "To",
        "start_offset": 618,
        "end_offset": 620,
        "start": 160.315,
        "end": 160.715,
        "score": -1.5545
      },
      {
        "word": "downgrade",
        "start_offset": 621,
        "end_offset": 630,
        "start": 162.315,
        "end": 164.756,
        "score": -1.0753
      },
      {
        "word": "these",
        "start_offset": 631,
        "end_offset": 636,
        "start": 165.856,
        "end": 166.396,
        "score": -0.8023
      },
      {
        "word": "experiences",
        "start_offset": 637,
        "end_offset": 648,
        "start": 167.036,
        "end": 169.036,
        "score": -1.0045
      },
      {
        "word": "by",
        "start_offset": 649,
        "end_offset": 651,
        "start": 170.136,
        "end": 170.576,
        "score": -1.0348
      },
      {
        "word": "the",
        "start_offset": 652,
        "end_offset": 655,
        "start": 170.876,
        "end": 170.996,
        "score": -2.9404
      },
      {
        "word": "use",
        "start_offset": 656,
        "end_offset": 659,
        "start": 171.576,
        "end": 172.056,
        "score": -3.1309
      },
      {
        "word": "of",
        "start_offset": 660,
        "end_offset": 662,
        "start": 172.896,
        "end": 173.157,
        "score": -6.322
      },
      {
        "word": "intellect",
        "start_offset": 663,
        "end_offset": 672,
        "start": 173.817,
        "end": 175.177,
        "score": -0.8457
      },
      {
        "word": "or",
        "start_offset": 673,
        "end_offset": 675,
        "start": 176.597,
        "end": 176.837,
        "score": -0.7368
      },
      {
        "word": "the",
        "start_offset": 676,
        "end_offset": 679,
        "start": 177.217,
        "end": 177.337,
        "score": -3.1126
      },
      {
        "word": "disciplines",
        "start_offset": 680,
        "end_offset": 691,
        "start": 177.797,
        "end": 179.137,
        "score": -1.9717
      },
      {
        "word": "of",
        "start_offset": 692,
        "end_offset": 694,
        "start": 180.077,
        "end": 180.357,
        "score": -6.2119
      },
      {
        "word": "will",
        "start_offset": 695,
        "end_offset": 699,
        "start": 180.757,
        "end": 181.157,
        "score": -1.126
      },
      {
        "word": "is",
        "start_offset": 700,
        "end_offset": 702,
        "start": 183.037,
        "end": 183.457,
        "score": -5.8689
      },
      {
        "word": "to",
        "start_offset": 703,
        "end_offset": 705,
        "start": 183.978,
        "end": 184.338,
        "score": -1.0844
      },
      {
        "word": "invite",
        "start_offset": 706,
        "end_offset": 712,
        "start": 185.118,
        "end": 186.058,
        "score": -1.1499
      },
      {
        "word": "the",
        "start_offset": 713,
        "end_offset": 716,
        "start": 187.238,
        "end": 187.378,
        "score": -0.7921
      },
      {
        "word": "prolonging",
        "start_offset": 717,
        "end_offset": 727,
        "start": 187.798,
        "end": 189.378,
        "score": -0.7427
      },
      {
        "word": "of",
        "start_offset": 728,
        "end_offset": 730,
        "start": 190.638,
        "end": 190.978,
        "score": -6.0375
      },
      {
        "word": "the",
        "start_offset": 731,
        "end_offset": 734,
        "start": 191.718,
        "end": 191.878,
        "score": -0.8325
      },
      {
        "word": "effects.",
        "start_offset": 735,
        "end_offset": 743,
        "start": 192.738,
        "end": 193.678,
        "score": -2.2142
      },
      {
        "word": "Far",
        "start_offset": 744,
        "end_offset": 747,
        "start": 195.299,
        "end": 195.739,
        "score": -3.9524
      },
      {
        "word": "better",
        "start_offset": 748,
        "end_offset": 754,
        "start": 196.479,
        "end": 196.999,
        "score": -1.7193
      },
      {
        "word": "then",
        "start_offset": 755,
        "end_offset": 759,
        "start": 197.779,
        "end": 198.139,
        "score": -0.7925
      },
      {
        "word": "to",
        "start_offset": 760,
        "end_offset": 762,
        "start": 199.619,
        "end": 199.979,
        "score": -1.0429
      },
      {
        "word": "share",
        "start_offset": 763,
        "end_offset": 768,
        "start": 200.579,
        "end": 201.099,
        "score": -1.0966
      },
      {
        "word": "in",
        "start_offset": 769,
        "end_offset": 771,
        "start": 202.719,
        "end": 202.919,
        "score": -5.4236
      },
      {
        "word": "trust",
        "start_offset": 772,
        "end_offset": 777,
        "start": 203.439,
        "end": 204.119,
        "score": -1.9371
      },
      {
        "word": "such",
        "start_offset": 778,
        "end_offset": 782,
        "start": 205.46,
        "end": 205.86,
        "score": -3.3825
      },
      {
        "word": "experiences",
        "start_offset": 783,
        "end_offset": 794,
        "start": 206.98,
        "end": 209.1,
        "score": -1.1948
      },
      {
        "word": "and",
        "start_offset": 795,
        "end_offset": 798,
        "start": 210.6,
        "end": 210.88,
        "score": -3.6766
      },
      {
        "word": "join",
        "start_offset": 799,
        "end_offset": 803,
        "start": 211.36,
        "end": 211.86,
        "score": -2.2279
      },
      {
        "word": "hearts",
        "start_offset": 804,
        "end_offset": 810,
        "start": 212.7,
        "end": 213.36,
        "score": -1.1396
      },
      {
        "word": "and",
        "start_offset": 811,
        "end_offset": 814,
        "start": 214.8,
        "end": 215.161,
        "score": -0.8299
      },
      {
        "word": "souls",
        "start_offset": 815,
        "end_offset": 820,
        "start": 215.981,
        "end": 216.641,
        "score": -1.0905
      },
      {
        "word": "in",
        "start_offset": 821,
        "end_offset": 823,
        "start": 218.041,
        "end": 218.321,
        "score": -5.6609
      },
      {
        "word": "love",
        "start_offset": 824,
        "end_offset": 828,
        "start": 218.901,
        "end": 219.401,
        "score": -0.9594
      },
      {
        "word": "and",
        "start_offset": 829,
        "end_offset": 832,
        "start": 220.721,
        "end": 221.081,
        "score": -1.7043
      },
      {
        "word": "light",
        "start_offset": 833,
        "end_offset": 838,
        "start": 221.741,
        "end": 222.181,
        "score": -1.009
      },
      {
        "word": "with",
        "start_offset": 839,
        "end_offset": 843,
        "start": 223.701,
        "end": 224.081,
        "score": -2.7867
      },
      {
        "word": "compassion",
        "start_offset": 844,
        "end_offset": 854,
        "start": 224.221,
        "end": 225.541,
        "score": -0.7955
      },
      {
        "word": "for",
        "start_offset": 855,
        "end_offset": 858,
        "start": 226.882,
        "end": 227.222,
        "score": -3.7754
      },
      {
        "word": "the",
        "start_offset": 859,
        "end_offset": 862,
        "start": 227.382,
        "end": 227.482,
        "score": -0.798
      },
      {
        "word": "sender",
        "start_offset": 863,
        "end_offset": 869,
        "start": 227.862,
        "end": 228.602,
        "score": -0.8527
      },
      {
        "word": "and",
        "start_offset": 870,
        "end_offset": 873,
        "start": 230.622,
        "end": 230.962,
        "score": -3.3852
      },
      {
        "word": "armor",
        "start_offset": 874,
        "end_offset": 879,
        "start": 231.322,
        "end": 231.862,
        "score": -1.0742
      },
      {
        "word": "for",
        "start_offset": 880,
        "end_offset": 883,
        "start": 233.262,
        "end": 233.582,
        "score": -3.9848
      },
      {
        "word": "the",
        "start_offset": 884,
        "end_offset": 887,
        "start": 233.742,
        "end": 233.862,
        "score": -0.8294
      },
      {
        "word": "self.",
        "start_offset": 888,
        "end_offset": 893,
        "start": 233.882,
        "end": 234.662,
        "score": -2.634
      }
    ]
  },
  "metadata": {
    "source_file": "044-10.mp3",
    "audio_duration": 236.0425,
    "alignment_method": "ctc_forced_align",
    "model": "mms_fa"
  }
}