{
  "text": "Could you give me more information on the energy fields of the body as relates to the right and left brain and if this is somehow related to the pyramid shape as far as energy focusing goes? I am a little lost at exactly how to get into this line of questioning, so I will ask that question. I am Ra. We are similarly at a loss at this line of answering. We may say that the pyramid shape is but one which focuses the instreamings of energy for use by entities which may become aware of these instreamings. We may say further that the shape of your physical brain is not significant as a shape for concentrating instreamings of energy. Please ask more specifically if you may that information you seek.",
  "timestamps": {
    "segment": [
      {
        "segment": "Could you give me more information on the energy fields of the body as relates to the right and left brain and if this is somehow related to the pyramid shape as far as energy focusing goes?",
        "start_offset": 0,
        "end_offset": 190,
        "start": 1.74,
        "end": 33.424
      },
      {
        "segment": "I am a little lost at exactly how to get into this line of questioning, so I will ask that question.",
        "start_offset": 191,
        "end_offset": 291,
        "start": 34.384,
        "end": 44.286
      },
      {
        "segment": "I am Ra.",
        "start_offset": 292,
        "end_offset": 300,
        "start": 44.526,
        "end": 46.686
      },
      {
        "segment": "We are similarly at a loss at this line of answering.",
        "start_offset": 301,
        "end_offset": 354,
        "start": 49.346,
        "end": 64.068
      },
      {
        "segment": "We may say that the pyramid shape is but one which focuses the instreamings of energy for use by entities which may become aware of these instreamings.",
        "start_offset": 355,
        "end_offset": 506,
        "start": 65.909,
        "end": 114.615
      },
      {
        "segment": "We may say further that the shape of your physical brain is not significant as a shape for concentrating instreamings of energy.",
        "start_offset": 507,
        "end_offset": 635,
        "start": 116.335,
        "end": 152.46
      },
      {
        "segment": "Please ask more specifically if you may that information you seek.",
        "start_offset": 636,
        "end_offset": 702,
        "start": 154.94,
        "end": 170.722
      }
    ],
    "word": [
      {
        "word": "Could",
        "start_offset": 0,
        "end_offset": 5,
        "start": 1.74,
        "end": 1.9,
        "score": -8.9323
      },
      {
        "word": "you",
        "start_offset": 6,
        "end_offset": 9,
        "start": 1.92,
        "end": 1.98,
        "score": -7.5108
      },
      {
        "word": "give",
        "start_offset": 10,
        "end_offset": 14,
        "start": 3.42,
        "end": 3.62,
        "score": -4.461
      },
      {
        "word": "me",
        "start_offset": 15,
        "end_offset": 17,
        "start": 3.64,
        "end": 3.7,
        "score": -4.6104
      },
      {
        "word": "more",
        "start_offset": 18,
        "end_offset": 22,
        "start": 3.8,
        "end": 4.001,
        "score": -3.9103
      },
      {
        "word": "information",
        "start_offset": 23,
        "end_offset": 34,
        "start": 4.061,
        "end": 4.781,
        "score": -3.9899
      },
      {
        "word": "on",
        "start_offset": 35,
        "end_offset": 37,
        "start": 4.961,
        "end": 5.121,
        "score": -6.0975
      },
      {
        "word": "the",
        "start_offset": 38,
        "end_offset": 41,
        "start": 6.721,
        "end": 6.861,
        "score": -4.1838
      },
      {
        "word": "energy",
        "start_offset": 42,
        "end_offset": 48,
        "start": 10.221,
        "end": 10.621,
        "score": -4.407
      },
      {
        "word": "fields",
        "start_offset": 49,
        "end_offset": 55,
        "start": 12.882,
        "end": 13.262,
        "score": -4.1835
      },
      {
        "word": "of",
        "start_offset": 56,
        "end_offset": 58,
        "start": 13.282,
        "end": 13.342,
        "score": -5.4706
      },
      {
        "word": "the",
        "start_offset": 59,
        "end_offset": 62,
        "start": 13.362,
        "end": 13.442,
        "score": -3.1453
      },
      {
        "word": "body",
        "start_offset": 63,
        "end_offset": 67,
        "start": 13.542,
        "end": 13.902,
        "score": -3.7516
      },
      {
        "word": "as",
        "start_offset": 68,
        "end_offset": 70,
        "start": 15.122,
        "end": 15.362,
        "score": -4.9063
      },
      {
        "word": "relates",
        "start_offset": 71,
        "end_offset": 78,
        "start": 17.702,
        "end": 18.122,
        "score": -1.7499
      },
      {
        "word": "to",
        "start_offset": 79,
        "end_offset": 81,
        "start": 18.222,
        "end": 18.302,
        "score": -2.7282
      },
      {
        "word": "the",
        "start_offset": 82,
        "end_offset": 85,
        "start": 18.422,
        "end": 18.522,
        "score": -2.9788
      },
      {
        "word": "right",
        "start_offset": 86,
        "end_offset": 91,
        "start": 19.623,
        "end": 19.863,
        "score": -3.4696
      },
      {
        "word": "and",
        "start_offset": 92,
        "end_offset": 95,
        "start": 19.903,
        "end": 20.003,
        "score": -4.1837
      },
      {
        "word": "left",
        "start_offset": 96,
        "end_offset": 100,
        "start": 20.103,
        "end": 20.403,
        "score": -2.6344
      },
      {
        "word": "brain",
        "start_offset": 101,
        "end_offset": 106,
        "start": 20.563,
        "end": 21.023,
        "score": -2.8881
      },
      {
        "word": "and",
        "start_offset": 107,
        "end_offset": 110,
        "start": 22.483,
        "end": 22.703,
        "score": -2.917
      },
      {
        "word": "if",
        "start_offset": 111,
        "end_offset": 113,
        "start": 22.843,
        "end": 22.923,
        "score": -4.0761
      },
      {
        "word": "this",
        "start_offset": 114,
        "end_offset": 118,
        "start": 23.003,
        "end": 23.223,
        "score": -2.522
      },
      {
        "word": "is",
        "start_offset": 119,
        "end_offset": 121,
        "start": 23.303,
        "end": 23.463,
        "score": -2.5658
      },
      {
        "word": "somehow",
        "start_offset": 122,
        "end_offset": 129,
        "start": 23.843,
        "end": 24.383,
        "score": -3.0094
      },
      {
        "word": "related",
        "start_offset": 130,
        "end_offset": 137,
        "start": 26.363,
        "end": 26.803,
        "score": -2.0301
      },
      {
        "word": "to",
        "start_offset": 138,
        "end_offset": 140,
        "start": 26.904,
        "end": 27.024,
        "score": -2.5738
      },
      {
        "word": "the",
        "start_offset": 141,
        "end_offset": 144,
        "start": 27.164,
        "end": 27.264,
        "score": -2.3552
      },
      {
        "word": "pyramid",
        "start_offset": 145,
        "end_offset": 152,
        "start": 27.364,
        "end": 27.944,
        "score": -2.1768
      },
      {
        "word": "shape",
        "start_offset": 153,
        "end_offset": 158,
        "start": 28.124,
        "end": 28.544,
        "score": -3.5952
      },
      {
        "word": "as",
        "start_offset": 159,
        "end_offset": 161,
        "start": 29.924,
        "end": 30.024,
        "score": -3.0211
      },
      {
        "word": "far",
        "start_offset": 162,
        "end_offset": 165,
        "start": 30.104,
        "end": 30.324,
        "score": -3.062
      },
      {
        "word": "as",
        "start_offset": 166,
        "end_offset": 168,
        "start": 30.404,
        "end": 30.524,
        "score": -2.9213
      },
      {
        "word": "energy",
        "start_offset": 169,
        "end_offset": 175,
        "start": 30.924,
        "end": 31.324,
        "score": -3.0996
      },
      {
        "word": "focusing",
        "start_offset": 176,
        "end_offset": 184,
        "start": 32.364,
        "end": 32.944,
        "score": -2.7369
      },
      {
        "word": "goes?",
        "start_offset": 185,
        "end_offset": 190,
        "start": 32.964,
        "end": 33.424,
        "score": -4.579
      },
      {
        "word": "I",
        "start_offset": 191,
        "end_offset": 192,
        "start": 34.384,
        "end": 34.404,
        "score": -7.9382
      },
      {
        "word": "am",
        "start_offset": 193,
        "end_offset": 195,
        "start": 34.424,
        "end": 34.565,
        "score": -2.9432
      },
      {
        "word": "a",
        "start_offset": 196,
        "end_offset": 197,
        "start": 34.605,
        "end": 34.625,
        "score": -2.6414
      },
      {
        "word": "little",
        "start_offset": 198,
        "end_offset": 204,
        "start": 34.725,
        "end": 34.965,
        "score": -3.3865
      },
      {
        "word": "lost",
        "start_offset": 205,
        "end_offset": 209,
        "start": 35.705,
        "end": 36.085,
        "score": -3.4991
      },
      {
        "word": "at",
        "start_offset": 210,
        "end_offset": 212,
        "start": 36.125,
        "end": 36.865,
        "score": -7.1578
      },
      {
        "word": "exactly",
        "start_offset": 213,
        "end_offset": 220,
        "start": 36.885,
        "end": 37.345,
        "score": -5.5164
      },
      {
        "word": "how",
        "start_offset": 221,
        "end_offset": 224,
        "start": 37.425,
        "end": 37.505,
        "score": -6.8197
      },
      {
        "word": "to",
        "start_offset": 225,
        "end_offset": 227,
        "start": 37.545,
        "end": 37.585,
        "score": -6.475
      },
      {
        "word": "get",
        "start_offset": 228,
        "end_offset": 231,
        "start": 37.645,
        "end": 37.785,
        "score": -4.294
      },
      {
        "word": "into",
        "start_offset": 232,
        "end_offset": 236,
        "start": 37.845,
        "end": 38.025,
        "score": -3.9428
      },
      {
        "word": "this",
        "start_offset": 237,
        "end_offset": 241,
        "start": 38.065,
        "end": 38.225,
        "score": -4.4892
      },
      {
        "word": "line",
        "start_offset": 242,
        "end_offset": 246,
        "start": 38.485,
        "end": 38.745,
        "score": -6.9148
      },
      {
        "word": "of",
        "start_offset": 247,
        "end_offset": 249,
        "start": 38.765,
        "end": 38.825,
        "score": -8.5034
      },
      {
        "word": "questioning,",
        "start_offset": 250,
        "end_offset": 262,
        "start": 38.845,
        "end": 39.285,
        "score": -7.31
      },
      {
        "word": "so",
        "start_offset": 263,
        "end_offset": 265,
        "start": 39.525,
        "end": 39.605,
        "score": -6.4672
      },
      {
        "word": "I",
        "start_offset": 266,
        "end_offset": 267,
        "start": 39.625,
        "end": 39.645,
        "score": -6.7772
      },
      {
        "word": "will",
        "start_offset": 268,
        "end_offset": 272,
        "start": 39.685,
        "end": 39.785,
        "score": -7.6235
      },
      {
        "word": "ask",
        "start_offset": 273,
        "end_offset": 276,
        "start": 39.845,
        "end": 40.025,
        "score": -6.307
      },
      {
        "word": "that",
        "start_offset": 277,
        "end_offset": 281,
        "start": 40.045,
        "end": 40.245,
        "score": -6.1343
      },
      {
        "word": "question.",
        "start_offset": 282,
        "end_offset": 291,
        "start": 40.345,
        "end": 44.286,
        "score": -7.4462
      },
      {
        "word": "I",
        "start_offset": 292,
        "end_offset": 293,
        "start": 44.526,
        "end": 44.546,
        "score": -1.0458
      },
      {
        "word": "am",
        "start_offset": 294,
        "end_offset": 296,
        "start": 45.486,
        "end": 45.826,
        "score": -2.0971
      },
      {
        "word": "Ra.",
        "start_offset": 297,
        "end_offset": 300,
        "start": 46.526,
        "end": 46.686,
        "score": -4.0162
      },
      {
        "word": "We",
        "start_offset": 301,
        "end_offset": 303,
        "start": 49.346,
        "end": 49.486,
        "score": -1.0537
      },
      {
        "word": "are",
        "start_offset": 304,
        "end_offset": 307,
        "start": 50.407,
        "end": 50.707,
        "score": -1.0703
      },
      {
        "word": "similarly",
        "start_offset": 308,
        "end_offset": 317,
        "start": 52.067,
        "end": 53.367,
        "score": -1.3521
      },
      {
        "word": "at",
        "start_offset": 318,
        "end_offset": 320,
        "start": 54.827,
        "end": 55.147,
        "score": -0.709
      },
      {
        "word": "a",
        "start_offset": 321,
        "end_offset": 322,
        "start": 55.407,
        "end": 55.427,
        "score": -0.7545
      },
      {
        "word": "loss",
        "start_offset": 323,
        "end_offset": 327,
        "start": 56.467,
        "end": 56.967,
        "score": -0.8754
      },
      {
        "word": "at",
        "start_offset": 328,
        "end_offset": 330,
        "start": 58.288,
        "end": 58.568,
        "score": -0.7046
      },
      {
        "word": "this",
        "start_offset": 331,
        "end_offset": 335,
        "start": 58.868,
        "end": 59.268,
        "score": -0.7221
      },
      {
        "word": "line",
        "start_offset": 336,
        "end_offset": 340,
        "start": 59.828,
        "end": 60.408,
        "score": -0.7078
      },
      {
        "word": "of",
        "start_offset": 341,
        "end_offset": 343,
        "start": 61.548,
        "end": 61.888,
        "score": -1.9474
      },
      {
        "word": "answering.",
        "start_offset": 344,
        "end_offset": 354,
        "start": 62.948,
        "end": 64.068,
        "score": -0.8941
      },
      {
        "word": "We",
        "start_offset": 355,
        "end_offset": 357,
        "start": 65.909,
        "end": 66.049,
        "score": -0.873
      },
      {
        "word": "may",
        "start_offset": 358,
        "end_offset": 361,
        "start": 67.249,
        "end": 67.569,
        "score": -0.7136
      },
      {
        "word": "say",
        "start_offset": 362,
        "end_offset": 365,
        "start": 68.069,
        "end": 68.469,
        "score": -0.7491
      },
      {
        "word": "that",
        "start_offset": 366,
        "end_offset": 370,
        "start": 69.809,
        "end": 70.229,
        "score": -0.7718
      },
      {
        "word": "the",
        "start_offset": 371,
        "end_offset": 374,
        "start": 70.869,
        "end": 71.029,
        "score": -1.0679
      },
      {
        "word": "pyramid",
        "start_offset": 375,
        "end_offset": 382,
        "start": 73.19,
        "end": 74.67,
        "score": -0.8348
      },
      {
        "word": "shape",
        "start_offset": 383,
        "end_offset": 388,
        "start": 75.39,
        "end": 75.99,
        "score": -0.9063
      },
      {
        "word": "is",
        "start_offset": 389,
        "end_offset": 391,
        "start": 77.27,
        "end": 77.67,
        "score": -0.7076
      },
      {
        "word": "but",
        "start_offset": 392,
        "end_offset": 395,
        "start": 78.15,
        "end": 78.55,
        "score": -0.7471
      },
      {
        "word": "one",
        "start_offset": 396,
        "end_offset": 399,
        "start": 79.29,
        "end": 79.57,
        "score": -0.7794
      },
      {
        "word": "which",
        "start_offset": 400,
        "end_offset": 405,
        "start": 81.091,
        "end": 81.591,
        "score": -0.7614
      },
      {
        "word": "focuses",
        "start_offset": 406,
        "end_offset": 413,
        "start": 82.891,
        "end": 84.371,
        "score": -0.7572
      },
      {
        "word": "the",
        "start_offset": 414,
        "end_offset": 417,
        "start": 86.251,
        "end": 86.391,
        "score": -0.7958
      },
      {
        "word": "instreamings",
        "start_offset": 418,
        "end_offset": 430,
        "start": 87.551,
        "end": 89.412,
        "score": -0.7854
      },
      {
        "word": "of",
        "start_offset": 431,
        "end_offset": 433,
        "start": 91.032,
        "end": 91.352,
        "score": -0.8254
      },
      {
        "word": "energy",
        "start_offset": 434,
        "end_offset": 440,
        "start": 92.492,
        "end": 93.132,
        "score": -2.2831
      },
      {
        "word": "for",
        "start_offset": 441,
        "end_offset": 444,
        "start": 94.912,
        "end": 95.372,
        "score": -0.7326
      },
      {
        "word": "use",
        "start_offset": 445,
        "end_offset": 448,
        "start": 96.233,
        "end": 96.693,
        "score": -0.8663
      },
      {
        "word": "by",
        "start_offset": 449,
        "end_offset": 451,
        "start": 97.913,
        "end": 98.433,
        "score": -1.4908
      },
      {
        "word": "entities",
        "start_offset": 452,
        "end_offset": 460,
        "start": 101.133,
        "end": 102.113,
        "score": -0.8315
      },
      {
        "word": "which",
        "start_offset": 461,
        "end_offset": 466,
        "start": 104.014,
        "end": 104.434,
        "score": -0.7772
      },
      {
        "word": "may",
        "start_offset": 467,
        "end_offset": 470,
        "start": 105.474,
        "end": 105.754,
        "score": -4.5064
      },
      {
        "word": "become",
        "start_offset": 471,
        "end_offset": 477,
        "start": 106.354,
        "end": 107.414,
        "score": -2.3193
      },
      {
        "word": "aware",
        "start_offset": 478,
        "end_offset": 483,
        "start": 108.414,
        "end": 109.154,
        "score": -0.8466
      },
      {
        "word": "of",
        "start_offset": 484,
        "end_offset": 486,
        "start": 110.294,
        "end": 110.614,
        "score": -6.2324
      },
      {
        "word": "these",
        "start_offset": 487,
        "end_offset": 492,
        "start": 111.274,
        "end": 111.815,
        "score": -1.2696
      },
      {
        "word": "instreamings.",
        "start_offset": 493,
        "end_offset": 506,
        "start": 113.175,
        "end": 114.615,
        "score": -1.6041
      },
      {
        "word": "We",
        "start_offset": 507,
        "end_offset": 509,
        "start": 116.335,
        "end": 116.455,
        "score": -4.8618
      },
      {
        "word": "may",
        "start_offset": 510,
        "end_offset": 513,
        "start": 116.955,
        "end": 117.235,
        "score": -4.2166
      },
      {
        "word": "say",
        "start_offset": 514,
        "end_offset": 517,
        "start": 117.695,
        "end": 118.115,
        "score": -3.6514
      },
      {
        "word": "further",
        "start_offset": 518,
        "end_offset": 525,
        "start": 119.176,
        "end": 119.996,
        "score": -1.2379
      },
      {
        "word": "that",
        "start_offset": 526,
        "end_offset": 530,
        "start": 121.396,
        "end": 121.796,
        "score": -2.7181
      },
      {
        "word": "the",
        "start_offset": 531,
        "end_offset": 534,
        "start": 122.336,
        "end": 122.476,
        "score": -3.0315
      },
      {
        "word": "shape",
        "start_offset": 535,
        "end_offset": 540,
        "start": 124.316,
        "end": 124.996,
        "score": -0.8179
      },
      {
        "word": "of",
        "start_offset": 541,
        "end_offset": 543,
        "start": 126.176,
        "end": 126.576,
        "score": -5.9676
      },
      {
        "word": "your",
        "start_offset": 544,
        "end_offset": 548,
        "start": 127.277,
        "end": 127.717,
        "score": -3.0333
      },
      {
        "word": "physical",
        "start_offset": 549,
        "end_offset": 557,
        "start": 128.937,
        "end": 129.917,
        "score": -2.21
      },
      {
        "word": "brain",
        "start_offset": 558,
        "end_offset": 563,
        "start": 131.057,
        "end": 131.717,
        "score": -0.7185
      },
      {
        "word": "is",
        "start_offset": 564,
        "end_offset": 566,
        "start": 133.137,
        "end": 133.537,
        "score": -6.3677
      },
      {
        "word": "not",
        "start_offset": 567,
        "end_offset": 570,
        "start": 134.317,
        "end": 134.758,
        "score": -0.825
      },
      {
        "word": "significant",
        "start_offset": 571,
        "end_offset": 582,
        "start": 135.858,
        "end": 137.618,
        "score": -1.5643
      },
      {
        "word": "as",
        "start_offset": 583,
        "end_offset": 585,
        "start": 138.858,
        "end": 139.298,
        "score": -0.7105
      },
      {
        "word": "a",
        "start_offset": 586,
        "end_offset": 587,
        "start": 139.398,
        "end": 139.418,
        "score": -8.3025
      },
      {
        "word": "shape",
        "start_offset": 588,
        "end_offset": 593,
        "start": 140.738,
        "end": 141.378,
        "score": -0.8245
      },
      {
        "word": "for",
        "start_offset": 594,
        "end_offset": 597,
        "start": 142.399,
        "end": 142.939,
        "score": -3.1208
      },
      {
        "word": "concentrating",
        "start_offset": 598,
        "end_offset": 611,
        "start": 143.839,
        "end": 145.979,
        "score": -1.6638
      },
      {
        "word": "instreamings",
        "start_offset": 612,
        "end_offset": 624,
        "start": 147.159,
        "end": 149.259,
        "score": -1.6804
      },
      {
        "word": "of",
        "start_offset": 625,
        "end_offset": 627,
        "start": 150.52,
        "end": 150.92,
        "score": -0.7952
      },
      {
        "word": "energy.",
        "start_offset": 628,
        "end_offset": 635,
        "start": 151.84,
        "end": 152.46,
        "score": -2.2116
      },
      {
        "word": "Please",
        "start_offset": 636,
        "end_offset": 642,
        "start": 154.94,
        "end": 155.78,
        "score": -1.2473
      },
      {
        "word": "ask",
        "start_offset": 643,
        "end_offset": 646,
        "start": 156.58,
        "end": 157.04,
        "score": -3.7261
      },
      {
        "word": "more",
        "start_offset": 647,
        "end_offset": 651,
        "start": 157.701,
        "end": 158.101,
        "score": -3.0716
      },
      {
        "word": "specifically",
        "start_offset": 652,
        "end_offset": 664,
        "start": 158.461,
        "end": 160.261,
        "score": -2.4982
      },
      {
        "word": "if",
        "start_offset": 665,
        "end_offset": 667,
        "start": 161.521,
        "end": 161.761,
        "score": -6.1788
      },
      {
        "word": "you",
        "start_offset": 668,
        "end_offset": 671,
        "start": 162.161,
        "end": 162.301,
        "score": -3.9318
      },
      {
        "word": "may",
        "start_offset": 672,
        "end_offset": 675,
        "start": 162.741,
        "end": 163.121,
        "score": -3.1814
      },
      {
        "word": "that",
        "start_offset": 676,
        "end_offset": 680,
        "start": 164.981,
        "end": 165.382,
        "score": -2.4328
      },
      {
        "word": "information",
        "start_offset": 681,
        "end_offset": 692,
        "start": 166.202,
        "end": 167.782,
        "score": -1.6103
      },
      {
        "word": "you",
        "start_offset": 693,
        "end_offset": 696,
        "start": 169.082,
        "end": 169.242,
        "score": -2.6254
      },
      {
        "word": "seek.",
        "start_offset": 697,
        "end_offset": 702,
        "start": 170.222,
        "end": 170.722,
        "score": -1.6781
      }
    ]
  },
  "metadata": {
    "source_file": "050-11.mp3",
    "audio_duration": 179.0433,
    "alignment_method": "ctc_forced_align",
    "model": "mms_fa"
  }
}