{
  "text": "Is the exercise of fire the best for the instrument, or is there anything better that we could do other than, of course, the things that you have already suggested to aid the instrument? I am Ra. Continue as you are at present. We cannot speak of the future as we may then affect it, but there is a great probability/possibility if you follow the path which you now tread that more efficacious methods for the entire group will be established. This instrument begins to show rapid distortion towards increase of pain. We, therefore, would offer time for any brief queries before we leave this working.",
  "timestamps": {
    "segment": [
      {
        "segment": "Is the exercise of fire the best for the instrument, or is there anything better that we could do other than, of course, the things that you have already suggested to aid the instrument?",
        "start_offset": 0,
        "end_offset": 186,
        "start": 2.98,
        "end": 34.383
      },
      {
        "segment": "I am Ra.",
        "start_offset": 187,
        "end_offset": 195,
        "start": 34.423,
        "end": 35.263
      },
      {
        "segment": "Continue as you are at present.",
        "start_offset": 196,
        "end_offset": 227,
        "start": 39.463,
        "end": 47.524
      },
      {
        "segment": "We cannot speak of the future as we may then affect it, but there is a great probability/possibility if you follow the path which you now tread that more efficacious methods for the entire group will be established.",
        "start_offset": 228,
        "end_offset": 443,
        "start": 49.244,
        "end": 117.63
      },
      {
        "segment": "This instrument begins to show rapid distortion towards increase of pain.",
        "start_offset": 444,
        "end_offset": 517,
        "start": 121.27,
        "end": 142.172
      },
      {
        "segment": "We, therefore, would offer time for any brief queries before we leave this working.",
        "start_offset": 518,
        "end_offset": 601,
        "start": 143.912,
        "end": 165.834
      }
    ],
    "word": [
      {
        "word": "Is",
        "start_offset": 0,
        "end_offset": 2,
        "start": 2.98,
        "end": 3.14,
        "score": -1.4465
      },
      {
        "word": "the",
        "start_offset": 3,
        "end_offset": 6,
        "start": 3.24,
        "end": 3.32,
        "score": -1.4634
      },
      {
        "word": "exercise",
        "start_offset": 7,
        "end_offset": 15,
        "start": 3.44,
        "end": 4.14,
        "score": -1.8355
      },
      {
        "word": "of",
        "start_offset": 16,
        "end_offset": 18,
        "start": 4.18,
        "end": 4.28,
        "score": -2.4814
      },
      {
        "word": "fire",
        "start_offset": 19,
        "end_offset": 23,
        "start": 5.04,
        "end": 5.4,
        "score": -3.4588
      },
      {
        "word": "the",
        "start_offset": 24,
        "end_offset": 27,
        "start": 5.42,
        "end": 5.5,
        "score": -5.4938
      },
      {
        "word": "best",
        "start_offset": 28,
        "end_offset": 32,
        "start": 10.021,
        "end": 10.441,
        "score": -2.9163
      },
      {
        "word": "for",
        "start_offset": 33,
        "end_offset": 36,
        "start": 12.761,
        "end": 13.041,
        "score": -4.0163
      },
      {
        "word": "the",
        "start_offset": 37,
        "end_offset": 40,
        "start": 17.041,
        "end": 17.141,
        "score": -3.2856
      },
      {
        "word": "instrument,",
        "start_offset": 41,
        "end_offset": 52,
        "start": 17.261,
        "end": 17.782,
        "score": -2.8927
      },
      {
        "word": "or",
        "start_offset": 53,
        "end_offset": 55,
        "start": 17.942,
        "end": 18.062,
        "score": -4.7629
      },
      {
        "word": "is",
        "start_offset": 56,
        "end_offset": 58,
        "start": 19.642,
        "end": 19.742,
        "score": -3.8415
      },
      {
        "word": "there",
        "start_offset": 59,
        "end_offset": 64,
        "start": 19.782,
        "end": 19.962,
        "score": -4.0332
      },
      {
        "word": "anything",
        "start_offset": 65,
        "end_offset": 73,
        "start": 19.982,
        "end": 20.362,
        "score": -4.9671
      },
      {
        "word": "better",
        "start_offset": 74,
        "end_offset": 80,
        "start": 20.782,
        "end": 21.082,
        "score": -8.4853
      },
      {
        "word": "that",
        "start_offset": 81,
        "end_offset": 85,
        "start": 21.142,
        "end": 21.502,
        "score": -8.3578
      },
      {
        "word": "we",
        "start_offset": 86,
        "end_offset": 88,
        "start": 21.522,
        "end": 21.582,
        "score": -8.9484
      },
      {
        "word": "could",
        "start_offset": 89,
        "end_offset": 94,
        "start": 22.982,
        "end": 23.182,
        "score": -8.2266
      },
      {
        "word": "do",
        "start_offset": 95,
        "end_offset": 97,
        "start": 23.222,
        "end": 23.322,
        "score": -7.4051
      },
      {
        "word": "other",
        "start_offset": 98,
        "end_offset": 103,
        "start": 23.922,
        "end": 24.142,
        "score": -6.1117
      },
      {
        "word": "than,",
        "start_offset": 104,
        "end_offset": 109,
        "start": 24.202,
        "end": 24.382,
        "score": -4.0646
      },
      {
        "word": "of",
        "start_offset": 110,
        "end_offset": 112,
        "start": 24.662,
        "end": 24.702,
        "score": -7.4784
      },
      {
        "word": "course,",
        "start_offset": 113,
        "end_offset": 120,
        "start": 24.742,
        "end": 25.062,
        "score": -7.3925
      },
      {
        "word": "the",
        "start_offset": 121,
        "end_offset": 124,
        "start": 25.102,
        "end": 25.202,
        "score": -8.1797
      },
      {
        "word": "things",
        "start_offset": 125,
        "end_offset": 131,
        "start": 25.742,
        "end": 25.942,
        "score": -6.6781
      },
      {
        "word": "that",
        "start_offset": 132,
        "end_offset": 136,
        "start": 25.962,
        "end": 26.102,
        "score": -7.9831
      },
      {
        "word": "you",
        "start_offset": 137,
        "end_offset": 140,
        "start": 26.122,
        "end": 26.182,
        "score": -4.1042
      },
      {
        "word": "have",
        "start_offset": 141,
        "end_offset": 145,
        "start": 26.242,
        "end": 26.362,
        "score": -7.1893
      },
      {
        "word": "already",
        "start_offset": 146,
        "end_offset": 153,
        "start": 26.382,
        "end": 26.542,
        "score": -5.5377
      },
      {
        "word": "suggested",
        "start_offset": 154,
        "end_offset": 163,
        "start": 26.642,
        "end": 27.282,
        "score": -2.7765
      },
      {
        "word": "to",
        "start_offset": 164,
        "end_offset": 166,
        "start": 28.262,
        "end": 28.342,
        "score": -7.2069
      },
      {
        "word": "aid",
        "start_offset": 167,
        "end_offset": 170,
        "start": 29.003,
        "end": 29.163,
        "score": -7.8525
      },
      {
        "word": "the",
        "start_offset": 171,
        "end_offset": 174,
        "start": 29.183,
        "end": 29.263,
        "score": -6.1884
      },
      {
        "word": "instrument?",
        "start_offset": 175,
        "end_offset": 186,
        "start": 29.363,
        "end": 34.383,
        "score": -6.245
      },
      {
        "word": "I",
        "start_offset": 187,
        "end_offset": 188,
        "start": 34.423,
        "end": 34.443,
        "score": -8.1908
      },
      {
        "word": "am",
        "start_offset": 189,
        "end_offset": 191,
        "start": 35.103,
        "end": 35.143,
        "score": -6.1586
      },
      {
        "word": "Ra.",
        "start_offset": 192,
        "end_offset": 195,
        "start": 35.163,
        "end": 35.263,
        "score": -5.5243
      },
      {
        "word": "Continue",
        "start_offset": 196,
        "end_offset": 204,
        "start": 39.463,
        "end": 40.383,
        "score": -0.7645
      },
      {
        "word": "as",
        "start_offset": 205,
        "end_offset": 207,
        "start": 41.744,
        "end": 42.144,
        "score": -0.8737
      },
      {
        "word": "you",
        "start_offset": 208,
        "end_offset": 211,
        "start": 42.824,
        "end": 42.964,
        "score": -0.8486
      },
      {
        "word": "are",
        "start_offset": 212,
        "end_offset": 215,
        "start": 43.804,
        "end": 44.084,
        "score": -0.8237
      },
      {
        "word": "at",
        "start_offset": 216,
        "end_offset": 218,
        "start": 45.184,
        "end": 45.424,
        "score": -0.8871
      },
      {
        "word": "present.",
        "start_offset": 219,
        "end_offset": 227,
        "start": 46.764,
        "end": 47.524,
        "score": -0.9483
      },
      {
        "word": "We",
        "start_offset": 228,
        "end_offset": 230,
        "start": 49.244,
        "end": 49.384,
        "score": -0.7572
      },
      {
        "word": "cannot",
        "start_offset": 231,
        "end_offset": 237,
        "start": 50.544,
        "end": 51.264,
        "score": -0.7084
      },
      {
        "word": "speak",
        "start_offset": 238,
        "end_offset": 243,
        "start": 52.104,
        "end": 52.625,
        "score": -0.795
      },
      {
        "word": "of",
        "start_offset": 244,
        "end_offset": 246,
        "start": 53.845,
        "end": 54.105,
        "score": -0.8759
      },
      {
        "word": "the",
        "start_offset": 247,
        "end_offset": 250,
        "start": 54.405,
        "end": 54.545,
        "score": -0.962
      },
      {
        "word": "future",
        "start_offset": 251,
        "end_offset": 257,
        "start": 56.765,
        "end": 57.385,
        "score": -0.7789
      },
      {
        "word": "as",
        "start_offset": 258,
        "end_offset": 260,
        "start": 59.225,
        "end": 59.565,
        "score": -0.7547
      },
      {
        "word": "we",
        "start_offset": 261,
        "end_offset": 263,
        "start": 59.925,
        "end": 60.085,
        "score": -0.7766
      },
      {
        "word": "may",
        "start_offset": 264,
        "end_offset": 267,
        "start": 60.845,
        "end": 61.165,
        "score": -0.7147
      },
      {
        "word": "then",
        "start_offset": 268,
        "end_offset": 272,
        "start": 62.765,
        "end": 63.085,
        "score": -0.8616
      },
      {
        "word": "affect",
        "start_offset": 273,
        "end_offset": 279,
        "start": 64.646,
        "end": 65.406,
        "score": -0.8328
      },
      {
        "word": "it,",
        "start_offset": 280,
        "end_offset": 283,
        "start": 65.926,
        "end": 66.146,
        "score": -0.7199
      },
      {
        "word": "but",
        "start_offset": 284,
        "end_offset": 287,
        "start": 67.626,
        "end": 67.946,
        "score": -0.7152
      },
      {
        "word": "there",
        "start_offset": 288,
        "end_offset": 293,
        "start": 68.706,
        "end": 69.086,
        "score": -0.9055
      },
      {
        "word": "is",
        "start_offset": 294,
        "end_offset": 296,
        "start": 70.346,
        "end": 70.686,
        "score": -0.8299
      },
      {
        "word": "a",
        "start_offset": 297,
        "end_offset": 298,
        "start": 71.706,
        "end": 71.726,
        "score": -0.7861
      },
      {
        "word": "great",
        "start_offset": 299,
        "end_offset": 304,
        "start": 73.026,
        "end": 73.486,
        "score": -0.8354
      },
      {
        "word": "probability/possibility",
        "start_offset": 305,
        "end_offset": 328,
        "start": 75.747,
        "end": 79.707,
        "score": -0.7248
      },
      {
        "word": "if",
        "start_offset": 329,
        "end_offset": 331,
        "start": 81.367,
        "end": 81.567,
        "score": -0.7549
      },
      {
        "word": "you",
        "start_offset": 332,
        "end_offset": 335,
        "start": 82.207,
        "end": 82.347,
        "score": -0.8348
      },
      {
        "word": "follow",
        "start_offset": 336,
        "end_offset": 342,
        "start": 84.187,
        "end": 84.667,
        "score": -0.7998
      },
      {
        "word": "the",
        "start_offset": 343,
        "end_offset": 346,
        "start": 85.687,
        "end": 85.827,
        "score": -0.8415
      },
      {
        "word": "path",
        "start_offset": 347,
        "end_offset": 351,
        "start": 86.527,
        "end": 86.987,
        "score": -2.9622
      },
      {
        "word": "which",
        "start_offset": 352,
        "end_offset": 357,
        "start": 88.688,
        "end": 89.068,
        "score": -0.73
      },
      {
        "word": "you",
        "start_offset": 358,
        "end_offset": 361,
        "start": 89.768,
        "end": 89.908,
        "score": -0.7518
      },
      {
        "word": "now",
        "start_offset": 362,
        "end_offset": 365,
        "start": 90.928,
        "end": 91.268,
        "score": -0.756
      },
      {
        "word": "tread",
        "start_offset": 366,
        "end_offset": 371,
        "start": 92.688,
        "end": 93.208,
        "score": -1.4642
      },
      {
        "word": "that",
        "start_offset": 372,
        "end_offset": 376,
        "start": 94.808,
        "end": 95.228,
        "score": -0.7218
      },
      {
        "word": "more",
        "start_offset": 377,
        "end_offset": 381,
        "start": 96.608,
        "end": 96.988,
        "score": -0.7406
      },
      {
        "word": "efficacious",
        "start_offset": 382,
        "end_offset": 393,
        "start": 98.428,
        "end": 100.009,
        "score": -1.311
      },
      {
        "word": "methods",
        "start_offset": 394,
        "end_offset": 401,
        "start": 101.449,
        "end": 102.229,
        "score": -0.7912
      },
      {
        "word": "for",
        "start_offset": 402,
        "end_offset": 405,
        "start": 104.389,
        "end": 104.809,
        "score": -0.7365
      },
      {
        "word": "the",
        "start_offset": 406,
        "end_offset": 409,
        "start": 105.869,
        "end": 106.009,
        "score": -0.8526
      },
      {
        "word": "entire",
        "start_offset": 410,
        "end_offset": 416,
        "start": 108.549,
        "end": 109.529,
        "score": -0.8383
      },
      {
        "word": "group",
        "start_offset": 417,
        "end_offset": 422,
        "start": 110.67,
        "end": 111.13,
        "score": -0.7772
      },
      {
        "word": "will",
        "start_offset": 423,
        "end_offset": 427,
        "start": 112.79,
        "end": 113.11,
        "score": -0.9465
      },
      {
        "word": "be",
        "start_offset": 428,
        "end_offset": 430,
        "start": 114.41,
        "end": 114.55,
        "score": -0.8481
      },
      {
        "word": "established.",
        "start_offset": 431,
        "end_offset": 443,
        "start": 116.13,
        "end": 117.63,
        "score": -0.7323
      },
      {
        "word": "This",
        "start_offset": 444,
        "end_offset": 448,
        "start": 121.27,
        "end": 121.69,
        "score": -0.8196
      },
      {
        "word": "instrument",
        "start_offset": 449,
        "end_offset": 459,
        "start": 123.191,
        "end": 124.331,
        "score": -0.7175
      },
      {
        "word": "begins",
        "start_offset": 460,
        "end_offset": 466,
        "start": 125.731,
        "end": 126.531,
        "score": -0.8522
      },
      {
        "word": "to",
        "start_offset": 467,
        "end_offset": 469,
        "start": 127.291,
        "end": 127.471,
        "score": -0.9079
      },
      {
        "word": "show",
        "start_offset": 470,
        "end_offset": 474,
        "start": 129.111,
        "end": 129.431,
        "score": -0.7889
      },
      {
        "word": "rapid",
        "start_offset": 475,
        "end_offset": 480,
        "start": 131.411,
        "end": 131.991,
        "score": -0.7289
      },
      {
        "word": "distortion",
        "start_offset": 481,
        "end_offset": 491,
        "start": 134.312,
        "end": 135.172,
        "score": -0.8383
      },
      {
        "word": "towards",
        "start_offset": 492,
        "end_offset": 499,
        "start": 136.472,
        "end": 137.172,
        "score": -0.7647
      },
      {
        "word": "increase",
        "start_offset": 500,
        "end_offset": 508,
        "start": 138.532,
        "end": 139.492,
        "score": -0.8922
      },
      {
        "word": "of",
        "start_offset": 509,
        "end_offset": 511,
        "start": 140.072,
        "end": 140.352,
        "score": -0.7838
      },
      {
        "word": "pain.",
        "start_offset": 512,
        "end_offset": 517,
        "start": 141.752,
        "end": 142.172,
        "score": -0.8078
      },
      {
        "word": "We,",
        "start_offset": 518,
        "end_offset": 521,
        "start": 143.912,
        "end": 144.032,
        "score": -0.9768
      },
      {
        "word": "therefore,",
        "start_offset": 522,
        "end_offset": 532,
        "start": 145.233,
        "end": 146.073,
        "score": -0.7763
      },
      {
        "word": "would",
        "start_offset": 533,
        "end_offset": 538,
        "start": 148.093,
        "end": 148.413,
        "score": -0.7534
      },
      {
        "word": "offer",
        "start_offset": 539,
        "end_offset": 544,
        "start": 149.993,
        "end": 150.393,
        "score": -2.8173
      },
      {
        "word": "time",
        "start_offset": 545,
        "end_offset": 549,
        "start": 151.253,
        "end": 151.773,
        "score": -0.7026
      },
      {
        "word": "for",
        "start_offset": 550,
        "end_offset": 553,
        "start": 152.193,
        "end": 152.533,
        "score": -0.7431
      },
      {
        "word": "any",
        "start_offset": 554,
        "end_offset": 557,
        "start": 153.993,
        "end": 154.213,
        "score": -3.0879
      },
      {
        "word": "brief",
        "start_offset": 558,
        "end_offset": 563,
        "start": 155.413,
        "end": 155.833,
        "score": -0.8255
      },
      {
        "word": "queries",
        "start_offset": 564,
        "end_offset": 571,
        "start": 157.474,
        "end": 158.274,
        "score": -1.0657
      },
      {
        "word": "before",
        "start_offset": 572,
        "end_offset": 578,
        "start": 159.734,
        "end": 160.414,
        "score": -0.7422
      },
      {
        "word": "we",
        "start_offset": 579,
        "end_offset": 581,
        "start": 160.854,
        "end": 160.974,
        "score": -0.7969
      },
      {
        "word": "leave",
        "start_offset": 582,
        "end_offset": 587,
        "start": 163.494,
        "end": 163.894,
        "score": -0.8928
      },
      {
        "word": "this",
        "start_offset": 588,
        "end_offset": 592,
        "start": 164.094,
        "end": 164.454,
        "score": -0.7717
      },
      {
        "word": "working.",
        "start_offset": 593,
        "end_offset": 601,
        "start": 165.354,
        "end": 165.834,
        "score": -0.7378
      }
    ]
  },
  "metadata": {
    "source_file": "075-40.mp3",
    "audio_duration": 166.0343,
    "alignment_method": "ctc_forced_align",
    "model": "mms_fa"
  }
}